curv/__init__.py
curv/_version.py
curv/version.py
curv-0.1.14.dist-info/METADATA
curv-0.1.14.dist-info/WHEEL
curv-0.1.14.dist-info/RECORD
