Metadata-Version: 2.4
Name: curv
Version: 0.1.14
Summary: Curv shared library for Curv RISC-V tooling
Author: Mike Goelzer
License: MIT
Classifier: Programming Language :: Python :: 3 :: Only
Requires-Python: >=3.10
Requires-Dist: curvpyutils>=0
